setup.py
huivo/__init__.py
huivo/thrift/__init__.py
huivo/thrift/client/Client.py
huivo/thrift/client/ClientFactory.py
huivo/thrift/client/Configurator.py
huivo/thrift/client/ConnectionPool.py
huivo/thrift/client/ReadWriteLock.py
huivo/thrift/client/ZkRegistry.py
huivo/thrift/client/__init__.py
huivo/thrift/common/__init__.py
huivo/thrift/common/constants.py
huivo/thrift/common/ttypes.py
huivo/thrift/test/Test.py
huivo/thrift/test/TestService.py
huivo/thrift/test/__init__.py
huivo/thrift/test/constants.py
huivo/thrift/test/ttypes.py
huivo_thrift.egg-info/PKG-INFO
huivo_thrift.egg-info/SOURCES.txt
huivo_thrift.egg-info/dependency_links.txt
huivo_thrift.egg-info/top_level.txt
test/__init__.py
test/constants.py
test/ttypes.py