Metadata-Version: 1.0
Name: huivo-thrift
Version: 1.0.0
Summary: huivo-thrift
Home-page: UNKNOWN
Author: UNKNOWN
Author-email: UNKNOWN
License: UNKNOWN
Platform: UNKNOWN
